setup.py
tug/__init__.py
tug/client.py
tug/main.py
tug.egg-info/PKG-INFO
tug.egg-info/SOURCES.txt
tug.egg-info/dependency_links.txt
tug.egg-info/entry_points.txt
tug.egg-info/requires.txt
tug.egg-info/top_level.txt