Metadata-Version: 1.0
Name: tug
Version: 0.3.0
Summary: Describe your infrastructure with yaml files
Home-page: https://github.com/metocean/tugboat-py
Author: MetOcean Solutions Ltd.
Author-email: t.coats@metocean.co.nz
License: Apache License 2.0
Platform: UNKNOWN
